escanervuln/__init__.py
escanervuln/cli.py
escanervuln/vuln_scanner.py
escanervuln/modules/__init__.py
escanervuln/modules/code_injection_detector.py
escanervuln/modules/deserialization_detector.py
escanervuln/modules/sql_injection_detector.py
escanervuln/modules/xss_detector.py
escanervuln-1.0.8.dist-info/METADATA
escanervuln-1.0.8.dist-info/WHEEL
escanervuln-1.0.8.dist-info/entry_points.txt
escanervuln-1.0.8.dist-info/top_level.txt
escanervuln-1.0.8.dist-info/RECORD
