Metadata-Version: 2.1
Name: escanervuln
Version: 1.0.8
Summary: Librería Modular de Detección de Vulnerabilidades en Python
Home-page: https://github.com/tuusuario/escanervuln
Author: Ignacio
Author-email: knjasu098@gmail.com
License: UNKNOWN
Platform: UNKNOWN
Classifier: Programming Language :: Python :: 3
Classifier: License :: OSI Approved :: MIT License
Classifier: Operating System :: OS Independent
Requires-Python: >=3.7
Requires-Dist: flask
Requires-Dist: pyyaml
